<?xml version="1.0" encoding="UTF-8"?>
<objects serializationModel="Studio.02.01.00">
	<object class="AudioFile" id="{7eb21090-9fbd-4920-b1fd-33fd56484835}">
		<property name="assetPath">
			<value>Stop.wav</value>
		</property>
		<property name="frequencyInKHz">
			<value>44.0999985</value>
		</property>
		<property name="channelCount">
			<value>2</value>
		</property>
		<property name="length">
			<value>2.1600000000000001</value>
		</property>
		<relationship name="masterAssetFolder">
			<destination>{5528fadc-328f-47a8-9f7f-51e983da4752}</destination>
		</relationship>
	</object>
</objects>
